[
  {
    "_id": "5e9664cff87ac15464c55f1b",
    "content": "If I had a gun with two bullets and I was in a room with Hitler, Bin Laden, and Toby, I would shoot Toby twice.",
    "character": [
      {
        "_id": "5e93b4a43af44260882e33b0",
        "firstname": "Michael",
        "lastname": "Scott",
        "__v": 0
      }
    ],
    "__v": 0
  },
  {
    "_id": "5e9666296a66e65486e2449b",
    "content": "I feel God in this Chili’s tonight.",
    "character": {
      "_id": "5e93b50a3af44260882e33b3",
      "firstname": "Pam",
      "lastname": "Beesly",
      "__v": 0
    },
    "__v": 0
  },
  {
    "_id": "5e96667c6a66e65486e2449d",
    "content": "Two eyes. Two ears. A chin. A mouth. Ten fingers. Two nipples. A butt, two kneecaps, a penis. I've just described to you the Loch Ness monster. And the reward for his capture? All the riches in Scotland. So I have one question: Why are you here?",
    "character": {
      "_id": "5e93b5813af44260882e33c0",
      "firstname": "Creed",
      "lastname": "Bratton",
      "__v": 0
    },
    "__v": 0
  },
  {
    "_id": "5e9666d76a66e65486e2449e",
    "content": "I am immensely proud of what I did for that turtle!",
    "character": {
      "_id": "5e93b5323af44260882e33b7",
      "firstname": "Kevin",
      "lastname": "Malone",
      "__v": 0
    },
    "__v": 0
  },
  {
    "_id": "5e9667836a66e65486e244a1",
    "content": "Last year, Creed asked me how to set up a blog. Wanting to protect the world from being exposed to Creed's brain, I opened up a Word document on his computer and put an address at the top. I've read some of it. Even for the Internet, it's... pretty shocking.",
    "character": {
      "_id": "5e93b5183af44260882e33b4",
      "firstname": "Ryan",
      "lastname": "Howard",
      "__v": 0
    },
    "__v": 0
  },
  {
    "_id": "5e9667cd6a66e65486e244a2",
    "content": "I don't talk trash, I talk smack. They're totally different. Trash talk is hypothetical, like: Your mom is so fat she can eat the internet. But smack talk is happening like right now. Like: You're ugly and I know it for a fact 'cause I got the evidence right there.",
    "character": {
      "_id": "5e93b51e3af44260882e33b5",
      "firstname": "Kelly",
      "lastname": "Kapoor",
      "__v": 0
    },
    "__v": 0
  }
]
